{"efSXuUiY6wDHp6xv1lEE9g==":"1200px-flag_of_the_united_nations.svg-122x81.png","ihlkf69UyfSmhSyJ1Jvc6w==":"jumbotron.jpg","HoeEF4HfT9nMa9Cg+v0y1w==":"02.jpg","GFyiqtznrzzoUpU07pOtiw==":"tumblr_ny0hlz7zeo1uw8s1mo2-500.gif","TWrXjj1UD5sOjfArY/3NwA==":"tumblr_ny0hlz7zeo1uw8s1mo2-501.gif","JpD0OmJ+TrdpICVbWOWBFg==":"purple%20mountains-1280x720.jpg","O1cJHfUPbPbAi9fY3dangw==":"un%20flags-1400x725.jpg","LT1M8y3Sv0xc/DdQJgS4Ww==":"ihsmunc-logo-122x124.png","ALfOIlqDB87VxaDie4Z0MQ==":"26197784-167981567149305-3989308206532771947-o-2000x1333.jpg","UbeRnbvJ0jxpyB5Npgub5A==":"26220131_186500722089530_8921555751688959702_n-960x640.jpg","8XVzN82V3wrLZzloZTeIZw==":"26195930_186502062089396_42272644562121508_n-960x640.jpg","hClxDrfwK36z8JYpRJTtRA==":"26167001_186501762089426_5414288621889071358_n-960x640.jpg","5+vHEC6u6OyR/FFaqvZ6OQ==":"26195803_186502338756035_1362065818769659386_n-960x640.jpg","wpY21HVCWf+v8ZH7HFfilA==":"26113700_186501605422775_2567416853044913800_n-960x640.jpg","CnYaCQLOOdPY24Xaxbd37Q==":"26168004_186502402089362_1367796734611582179_n-960x640.jpg","bBUO5YIdOSIbBtfUaD4FZQ==":"26056122_184953392244263_4118702463752426058_n-960x640.jpg","734eoyXqKFks3engI8DVew==":"26197784-167981567149305-3989308206532771947-o-1-2000x1333.jpg","ZYdYymJ92rm6k5xqgcnoVQ==":"ihsmunc%20logo-120x119.png","LprjluQpleScyzMsgCcMxw==":"books-1245690-1920-676x451.jpg","N47Gdgrjc//qGWwXOsczGA==":"conference-2705706-1920-676x451.jpg","+fxjKxEu/XkP6gnd0XeVTw==":"mbr-676x451.jpg","uuPTh9K6AxTJszzVPEahqQ==":"mbr-1-676x451.jpg","vSsRK5qnRx1+xzDomA5dDA==":"rawpixel-1055781-unsplash-2000x1341.jpg","3F0naa9CbHkJjeV1+0FeTw==":"laptop-3196481-1920-1920x1280.jpg","8dVsc27G6IFBzRCK7L4iVg==":"conference-2705706-1920-1920x1280.jpg","G6GxHjTJ6bm14j4U7yRxFQ==":"laptop-3196481-1920-676x451.jpg","Xx2DnqzqAZFUWBClmNKyNw==":"microphone-704255-1920-676x451.jpg","nat2+D7g/KLzUTtc8neYoA==":"un-flags-1-1400x725.jpg","/522pN+NcZXzQo4z91F9IQ==":"un-flags-2-1400x725.jpg","0OOE1Usrtktm437Z/qTMRQ==":"background2.jpg","NABkP9i4t4mIGSpFn73WIA==":"background1.jpg","aPQnwDVzVgGOizVHrZLrtA==":"26197784-167981567149305-3989308206532771947-o-2-2000x1333.jpg","s8xW6/2Lyn1rByakRkmPEw==":"26167001-186501762089426-5414288621889071358-n-1-960x640.jpg","6RBfgo86FJcQcCLLIwXN0A==":"mun%20story%20backdrop-1080x1920.jpg","LFPGufm0qsIrpIScmKoHHA==":"26113700-186501605422775-2567416853044913800-n-960x640.jpg","szsYbgRS4g6xKbzR52hGNg==":"26056122-184953392244263-4118702463752426058-n-960x640.jpg","iRZhOPCM/cMcXSI1t/aAPQ==":"26056122-184953392244263-4118702463752426058-n-1-960x640.jpg","kN42B1yTbRkEiJSpL85lZA==":"books-1617327-1920-1920x1080.jpg","MILGjumwbksc5w/pne+LJA==":"mbr-1920x1280.jpg","0EPEJ2bG0+65uCzo8KrlBg==":"mbr-1-1920x1280.jpg","b1VgyZtjf8+He6lRTNWxMw==":"mbr-1920x954.jpg","HzJ8WyDxMR7vXWT715GhmA==":"mbr-1920x1276.jpg","Brx/CbrpDj2vE8nOhf8ucg==":"mbr-1920x1081.jpg","PvcWzTh76Nl/4GisUpDVIg==":"mbr-2-1920x1280.jpg","OM0lChfdKCiv12eU9HeL8Q==":"img-761-2000x1333.jpg","l7yCR028n/n83jr+dRK+0A==":"yash-510x660.jpg","EwgKOJllJj4hJ3+NTm5Rfw==":"renwick-510x657.jpg","0K0/KRkxplF4rUeDILY+rQ==":"ananya-510x657.jpg","wo5Aj69bMsHsgg1xDh21jA==":"arnav-510x660.jpg","Pdj4GGI89KkRVQR3MISokQ==":"nikhil-510x660.jpg","Vpho0/g1ApWIlg8+6gmR9w==":"tie-690084-1920-510x340.jpg","fYg8yxZ0g3dtAQzKxU2Nfg==":"tie-690084-1921-510x340.jpg","yAxELxpdxRfACpnvyoiX1A==":"mystery-510x657.jpg","Brdmeuyem6GiIWrFChBxXQ==":"ma'am-510x657.jpg","AkU1LxWw+Cyxoq/RniZ7EQ==":"mun%20story%20backdrop-510x907.jpg","28TJBzikvmVzAACi6rfeYQ==":"empty-510x657.jpg","gfSlbkDEpz3KouTphMFTcw==":"rawpixel-670711-unsplash-2000x1333.jpg","/tDQM4vQf0Rzl+lJSZNozw==":"ashwin-510x657.jpg","X/bx8CFaE9Wo20UUbmlhhw==":"ashwin-1-510x657.jpg","JEOU4jgFAchaUDnhkZCguQ==":"ashwin-2-510x657.jpg","Wxsjx4CERAqbaBzZO1FSnQ==":"aaryan-510x657.jpg","bucYT4Mf0xjK1164EhjJeQ==":"aaryan-1-510x657.jpg","MfUe8R5DDHayFRoLR9A8yw==":"aaryan-2-510x657.jpg","HjhZs4nabLrwhuuAL93KKA==":"wht-1014x1803.jpg","h/mr/G8ZWhzwr/3M68oOCg==":"wht-1080x1920.jpg","9Grl9xry6xn2u5CU0NJ/NA==":"wht-1-1080x1920.jpg","kTQ99GEido+RlujKEueAsA==":"dscf3108-510x657.jpg","Kx4yn+8D5a681lsH3XdFng==":"sir-510x657.jpg"}